aws_credentials_merge/__init__.py
vault_aws_login/__init__.py
vault_aws_login/consul_template.py
vault_aws_login/context.py
vault_aws_login/vault.py
vault_aws_login-0.0.4.data/scripts/aws_credentials_merge
vault_aws_login-0.0.4.data/scripts/vault-aws-login
vault_aws_login-0.0.4.dist-info/LICENSE
vault_aws_login-0.0.4.dist-info/METADATA
vault_aws_login-0.0.4.dist-info/WHEEL
vault_aws_login-0.0.4.dist-info/top_level.txt
vault_aws_login-0.0.4.dist-info/RECORD
