Metadata-Version: 2.1
Name: vault-aws-login
Version: 0.0.4
Summary: Stay authenticated in awscli with vault
Home-page: https://github.com/nhtzr/vault-aws-login
Author: Ezequiel Rosas
Author-email: ezequiel.rosas@digitalonus.com
License: MIT
Platform: UNKNOWN
Classifier: Programming Language :: Python :: 3
Classifier: License :: OSI Approved :: MIT License
Classifier: Operating System :: OS Independent
Requires-Python: >=3.6
